{
  "description": null,
  "locations": [
    {
      "available": false,
      "enabled": false,
      "fqdn": "powerj7kmpzkdhjg4szvcxxgktgk36ezpjxvtosylrpey7svpmrjyuyd.onion",
      "lastscrape": "2025-06-01 21:19:12.061494",
      "slug": "http://powerj7kmpzkdhjg4szvcxxgktgk36ezpjxvtosylrpey7svpmrjyuyd.onion/",
      "title": " Dark Power Ransomware",
      "type": "DLS",
      "updated": "2023-03-15 06:44:24.214561"
    }
  ],
  "meta": null,
  "name": "darkpower",
  "parser": false,
  "profile": [],
  "tools": [],
  "ttps": [],
  "url": "https://www.ransomware.live/group/darkpower"
}