{
  "_victim_count": 155,
  "description": "Not a Ransomware Group",
  "locations": [
    {
      "available": false,
      "enabled": false,
      "fqdn": "handala.to",
      "lastscrape": "2025-06-26 12:00:04.838079",
      "slug": "https://handala.to/",
      "title": "",
      "type": "DLS",
      "updated": "2025-05-27 11:31:36.427890"
    },
    {
      "available": true,
      "enabled": true,
      "fqdn": "handala-hack.to",
      "http": {
        "error": null,
        "fetched_at": "2026-04-05T01:01:11+00:00",
        "final_url": "https://handala-hack.to/",
        "fingerprint": {
          "cdn": "9e749ec44f6ad42a-ARN",
          "content_length": null,
          "content_type": "text/html",
          "security_headers": {},
          "server": "cloudflare",
          "set_cookie_present": false,
          "via": null,
          "x_powered_by": null
        },
        "headers": {
          "alt-svc": "h3=\":443\"; ma=86400",
          "cf-ray": "9e749ec44f6ad42a-ARN",
          "connection": "keep-alive",
          "content-encoding": "br",
          "content-type": "text/html",
          "date": "Sun, 05 Apr 2026 01:01:11 GMT",
          "nel": "{\"report_to\":\"cf-nel\",\"success_fraction\":0.0,\"max_age\":604800}",
          "report-to": "{\"group\":\"cf-nel\",\"max_age\":604800,\"endpoints\":[{\"url\":\"https://a.nel.cloudflare.com/report/v4?s=FYY9imX52877MTVtUPSBiIrh6XRSpQJWyncsVsocBwUbQrtekFtn6vN4Gn62tsV24hKkaqDY1YcNhnbzgIBl4DyXQqofNj2dZHzkxXdjjl7Vo3DQT2y8T6cUW2xednajRSI%3D\"}]}",
          "server": "cloudflare"
        },
        "http_version": "HTTP/1.1",
        "redirect_chain": [],
        "start_url": "https://handala-hack.to/",
        "status": 200
      },
      "lastscrape": "2026-04-05 01:01:11.192618",
      "slug": "https://handala-hack.to/",
      "title": "This Website Has Been Seized",
      "type": "DLS",
      "updated": "2026-04-05 01:01:11.192618"
    },
    {
      "available": false,
      "enabled": true,
      "fqdn": "vmjfieomxhnfjba57sd6jjws2ogvowjgxhhfglsikqvvrnrajbmpxqqd.onion",
      "http": {
        "error": "Host unreachable",
        "fetched_at": "2026-04-05T01:30:28+00:00",
        "final_url": null,
        "fingerprint": {},
        "headers": {},
        "http_version": null,
        "redirect_chain": [],
        "start_url": "http://vmjfieomxhnfjba57sd6jjws2ogvowjgxhhfglsikqvvrnrajbmpxqqd.onion",
        "status": null
      },
      "lastscrape": "2026-04-05 01:30:28.275296",
      "slug": "http://vmjfieomxhnfjba57sd6jjws2ogvowjgxhhfglsikqvvrnrajbmpxqqd.onion",
      "title": "",
      "type": "DLS",
      "updated": "2026-03-30 09:31:13.655761"
    },
    {
      "available": false,
      "enabled": true,
      "fqdn": "handala-team.to",
      "http": {
        "error": "Host unreachable",
        "fetched_at": "2026-04-05T01:30:52+00:00",
        "final_url": null,
        "fingerprint": {},
        "headers": {},
        "http_version": null,
        "redirect_chain": [],
        "start_url": "http://handala-team.to",
        "status": null
      },
      "lastscrape": "2026-04-05 01:30:51.983345",
      "slug": "http://handala-team.to",
      "title": "Error Response Page",
      "type": "DLS",
      "updated": "2026-04-01 14:03:40.533112"
    },
    {
      "available": true,
      "enabled": true,
      "fqdn": "handala-hack.tw",
      "http": {
        "error": null,
        "fetched_at": "2026-04-05T00:31:50+00:00",
        "final_url": "http://handala-hack.tw",
        "fingerprint": {
          "cdn": null,
          "content_length": "988",
          "content_type": "text/html",
          "security_headers": {},
          "server": "EdgeOne_L7S_OC",
          "set_cookie_present": true,
          "via": null,
          "x_powered_by": null
        },
        "headers": {
          "cache-control": "no-cache",
          "connection": "keep-alive",
          "content-length": "988",
          "content-type": "text/html",
          "date": "Sun, 05 Apr 2026 00:31:50 GMT",
          "eo-log-uuid": "274532252533367414",
          "server": "EdgeOne_L7S_OC",
          "set-cookie": "path=/"
        },
        "http_version": "HTTP/1.1",
        "redirect_chain": [],
        "start_url": "http://handala-hack.tw",
        "status": 200
      },
      "lastscrape": "2026-04-05 00:31:50.423838",
      "slug": "http://handala-hack.tw",
      "title": "Security Verification",
      "type": "DLS",
      "updated": "2026-04-05 00:31:50.423838"
    }
  ],
  "meta": null,
  "name": "handala",
  "parser": true,
  "profile": [],
  "tools": [],
  "ttps": [],
  "url": "https://www.ransomware.live/group/handala"
}