{
  "_victim_count": 26,
  "locations": [
    {
      "available": true,
      "enabled": true,
      "fqdn": "kelvinsecteamcyber.wixsite.com",
      "http": {
        "error": null,
        "fetched_at": "2026-03-29T09:31:22+00:00",
        "final_url": "https://kelvinsecteamcyber.wixsite.com/my-site/items",
        "fingerprint": {
          "cdn": null,
          "content_length": null,
          "content_type": "text/html; charset=utf-8",
          "security_headers": {
            "x-content-type-options": "nosniff"
          },
          "server": "Pepyaka",
          "set_cookie_present": false,
          "via": "1.1 google",
          "x_powered_by": null
        },
        "headers": {
          "age": "0",
          "alt-svc": "h3=\":443\"; ma=2592000,h3-29=\":443\"; ma=2592000",
          "content-encoding": "br",
          "content-type": "text/html; charset=utf-8",
          "date": "Sun, 29 Mar 2026 09:31:23 GMT",
          "glb-x-seen-by": "zj+a2E71qOCweet+2KoAwKsDXK9Yj1hJlUA0MXxzy6E=",
          "server": "Pepyaka",
          "server-timing": "cache;desc=miss, varnish;desc=miss, dc;desc=virginia-pub_g",
          "transfer-encoding": "chunked",
          "vary": "Accept-Encoding",
          "via": "1.1 google",
          "x-cache-status": "MISS",
          "x-content-type-options": "nosniff",
          "x-seen-by": "pmHZlB45NPy7b1VBAukQrewfbs+7qUVAqsIx00yI78k=,Ua1iSBCTq7qSXjmRCGE1N2ULFjA7whvbPefXEdiEM0aTJbQZXz+JisZOpyMIlD4PKOrmrHsSqv/Qsp2HwJAGxA==,2d58ifebGbosy5xc+FRaljxIN+BEL+cJMWCG2ZlPmsoEkhUn2BMbT3DrXDanJKy/dCFVoVD5X0ODpm18eJlWw1iB5QmpRe2J37zq9nDD6cs=,2UNV7KOq4oGjA5+PKsX47E0aocE5jZ+SHqU8+c6ueiQxwy5Yb789UDkEfaJNWrtQ,2UNV7KOq4oGjA5+PKsX47M9gmxcp/Ds+7yz4ddgAm6dBgoOYGa1MpluGPPjG4/Tb,/B3VgDtICCNDWQOEWfZmMnir5Bff9skTETytbgZGjlc=,7qRhWu5NOm1hVs7o3HvocND8qNfTXOY8xCsvq/VSIqAj6r0AZAMucqm4C7kwBEyaCqyQU298LM+v5RfDrwbqDw==",
          "x-wix-cache-control": "public, max-age=30",
          "x-wix-request-id": "1774776683.270136768731321"
        },
        "http_version": "HTTP/1.1",
        "redirect_chain": [],
        "start_url": "https://kelvinsecteamcyber.wixsite.com/my-site/items",
        "status": 404
      },
      "lastscrape": "2026-03-29 09:31:22.755358",
      "slug": "https://kelvinsecteamcyber.wixsite.com/my-site/items",
      "title": "404 Error: Page Not Found | Wix.com",
      "type": "DLS",
      "updated": "2026-03-29 09:31:22.755358"
    }
  ],
  "meta": "not a ransomware group",
  "name": "kelvinsecurity",
  "parser": false,
  "profile": [],
  "tools": [],
  "ttps": [],
  "url": "https://www.ransomware.live/group/kelvinsecurity"
}