{
  "_victim_count": 15,
  "altname": null,
  "date": "2025-11-29",
  "description": null,
  "extensions ": null,
  "lineage": null,
  "locations": [
    {
      "available": true,
      "enabled": true,
      "fqdn": "tridentfrdy6jydwywfx4vx422vnto7pktao2gyx2qdcwjanogq454ad.onion",
      "http": {
        "error": null,
        "fetched_at": "2026-04-24T00:32:02+00:00",
        "final_url": "http://tridentfrdy6jydwywfx4vx422vnto7pktao2gyx2qdcwjanogq454ad.onion/articles",
        "fingerprint": {
          "cdn": null,
          "content_length": null,
          "content_type": "text/html; charset=utf-8",
          "security_headers": {},
          "server": "Kestrel",
          "set_cookie_present": false,
          "via": null,
          "x_powered_by": null
        },
        "headers": {
          "content-type": "text/html; charset=utf-8",
          "date": "Fri, 24 Apr 2026 00:32:02 GMT",
          "server": "Kestrel"
        },
        "http_version": "HTTP/1.1",
        "redirect_chain": [],
        "start_url": "http://tridentfrdy6jydwywfx4vx422vnto7pktao2gyx2qdcwjanogq454ad.onion/articles",
        "status": 200
      },
      "lastscrape": "2026-04-24 00:32:02.873252",
      "slug": "http://tridentfrdy6jydwywfx4vx422vnto7pktao2gyx2qdcwjanogq454ad.onion/articles",
      "title": "TridentLocker",
      "type": "DLS",
      "updated": "2026-04-24 00:32:02.873252"
    },
    {
      "available": true,
      "enabled": true,
      "fqdn": "tridentfrdy6jydwywfx4vx422vnto7pktao2gyx2qdcwjanogq454ad.onion",
      "http": {
        "error": null,
        "fetched_at": "2026-04-24T00:33:05+00:00",
        "final_url": "http://tridentfrdy6jydwywfx4vx422vnto7pktao2gyx2qdcwjanogq454ad.onion",
        "fingerprint": {
          "cdn": null,
          "content_length": null,
          "content_type": "text/html; charset=utf-8",
          "security_headers": {},
          "server": "Kestrel",
          "set_cookie_present": false,
          "via": null,
          "x_powered_by": null
        },
        "headers": {
          "content-type": "text/html; charset=utf-8",
          "date": "Fri, 24 Apr 2026 00:33:05 GMT",
          "server": "Kestrel"
        },
        "http_version": "HTTP/1.1",
        "redirect_chain": [],
        "start_url": "http://tridentfrdy6jydwywfx4vx422vnto7pktao2gyx2qdcwjanogq454ad.onion",
        "status": 200
      },
      "lastscrape": "2026-04-24 00:33:05.941029",
      "slug": "http://tridentfrdy6jydwywfx4vx422vnto7pktao2gyx2qdcwjanogq454ad.onion",
      "title": "TridentLocker",
      "type": "Chat",
      "updated": "2026-04-24 00:33:05.941029"
    }
  ],
  "meta": null,
  "name": "tridentlocker",
  "profile": [],
  "tools": [],
  "ttps": [],
  "type": {
    "raas": false
  },
  "url": "https://www.ransomware.live/group/tridentlocker"
}