{
  "contact": null,
  "date": "2025-03-06",
  "description": null,
  "locations": [
    {
      "available": false,
      "enabled": false,
      "fqdn": "xtxtpqpyaaek4p4525ksepyyy75gfvi47fptm2gftw7cn656rnfhzdqd.onion",
      "lastscrape": "2025-06-01 21:19:12.636054",
      "slug": "http://xtxtpqpyaaek4p4525ksepyyy75gfvi47fptm2gftw7cn656rnfhzdqd.onion/leaks",
      "title": "",
      "type": "DLS",
      "updated": "2025-03-07 13:01:26.784550"
    },
    {
      "available": true,
      "enabled": true,
      "fqdn": "weyhro.hk",
      "http": {
        "error": null,
        "fetched_at": "2026-03-20T19:01:40+00:00",
        "final_url": "https://weyhro.hk/leaks",
        "fingerprint": {
          "cdn": "9df6f79d88f43793-OTP",
          "content_length": null,
          "content_type": "text/html; charset=utf-8",
          "security_headers": {},
          "server": "cloudflare",
          "set_cookie_present": false,
          "via": null,
          "x_powered_by": "Next.js"
        },
        "headers": {
          "alt-svc": "h3=\":443\"; ma=86400",
          "cache-control": "private, no-cache, no-store, max-age=0, must-revalidate",
          "cf-cache-status": "DYNAMIC",
          "cf-ray": "9df6f79d88f43793-OTP",
          "connection": "keep-alive",
          "content-encoding": "br",
          "content-type": "text/html; charset=utf-8",
          "date": "Fri, 20 Mar 2026 19:01:45 GMT",
          "nel": "{\"report_to\":\"cf-nel\",\"success_fraction\":0.0,\"max_age\":604800}",
          "onion-location": "http://weyhro27ruifvuqkk3hxzcrtxv2lsalntxgkv6q2j3znkhdqudz54rqd.onion",
          "report-to": "{\"group\":\"cf-nel\",\"max_age\":604800,\"endpoints\":[{\"url\":\"https://a.nel.cloudflare.com/report/v4?s=tfVyGm4LuCVu8pfC7Gj88IaFNZzPgsUO31go0M5l0J5KZ4V%2BmcKHud63hxxkLKZsbDTJAyOeys%2BanFAbkiAG4N65UmGJWgI%3D\"}]}",
          "server": "cloudflare",
          "speculation-rules": "\"/cdn-cgi/speculation\"",
          "vary": "RSC, Next-Router-State-Tree, Next-Router-Prefetch, Next-Url, Accept-Encoding",
          "x-powered-by": "Next.js"
        },
        "http_version": "HTTP/1.1",
        "redirect_chain": [
          {
            "location": "/leaks",
            "status": 308
          }
        ],
        "start_url": "https://weyhro.hk/leaks/",
        "status": 200
      },
      "lastscrape": "2026-03-20 19:01:40.146987",
      "slug": "https://weyhro.hk/leaks/",
      "title": "Weyhro",
      "type": "DLS",
      "updated": "2026-03-20 19:01:40.146987"
    },
    {
      "available": false,
      "enabled": false,
      "fqdn": "weyhro27ruifvuqkk3hxzcrtxv2lsalntxgkv6q2j3znkhdqudz54rqd.onion",
      "http": {
        "error": "Host unreachable",
        "fetched_at": "2025-12-25T13:30:20+00:00",
        "final_url": null,
        "fingerprint": {},
        "headers": {},
        "http_version": null,
        "redirect_chain": [],
        "start_url": "http://weyhro27ruifvuqkk3hxzcrtxv2lsalntxgkv6q2j3znkhdqudz54rqd.onion/",
        "status": null
      },
      "lastscrape": "2025-12-25 13:30:19.763483",
      "slug": "http://weyhro27ruifvuqkk3hxzcrtxv2lsalntxgkv6q2j3znkhdqudz54rqd.onion/",
      "title": "Weyhro",
      "type": "DLS",
      "updated": "2025-11-25 13:02:26.269686"
    },
    {
      "available": false,
      "enabled": false,
      "fqdn": "weyhro27ruifvuqkk3hxzcrtxv2lsalntxgkv6q2j3znkhdqudz54rqd.onion",
      "http": {
        "error": "Host unreachable",
        "fetched_at": "2025-12-25T13:30:36+00:00",
        "final_url": null,
        "fingerprint": {},
        "headers": {},
        "http_version": null,
        "redirect_chain": [],
        "start_url": "http://weyhro27ruifvuqkk3hxzcrtxv2lsalntxgkv6q2j3znkhdqudz54rqd.onion/leaks/",
        "status": null
      },
      "lastscrape": "2025-12-25 13:30:36.198706",
      "slug": "http://weyhro27ruifvuqkk3hxzcrtxv2lsalntxgkv6q2j3znkhdqudz54rqd.onion/leaks/",
      "title": "Weyhro",
      "type": "DLS",
      "updated": "2025-11-25 13:03:28.149036"
    },
    {
      "available": true,
      "enabled": true,
      "fqdn": "weyhro.hk",
      "http": {
        "error": null,
        "fetched_at": "2026-03-20T19:02:49+00:00",
        "final_url": "https://weyhro.hk",
        "fingerprint": {
          "cdn": "9df6f92e3802bd47-AMS",
          "content_length": null,
          "content_type": "text/html; charset=utf-8",
          "security_headers": {},
          "server": "cloudflare",
          "set_cookie_present": false,
          "via": null,
          "x_powered_by": "Next.js"
        },
        "headers": {
          "alt-svc": "h3=\":443\"; ma=86400",
          "cache-control": "s-maxage=31536000, stale-while-revalidate",
          "cf-cache-status": "DYNAMIC",
          "cf-ray": "9df6f92e3802bd47-AMS",
          "connection": "keep-alive",
          "content-encoding": "br",
          "content-type": "text/html; charset=utf-8",
          "date": "Fri, 20 Mar 2026 19:02:49 GMT",
          "nel": "{\"report_to\":\"cf-nel\",\"success_fraction\":0.0,\"max_age\":604800}",
          "onion-location": "http://weyhro27ruifvuqkk3hxzcrtxv2lsalntxgkv6q2j3znkhdqudz54rqd.onion",
          "report-to": "{\"group\":\"cf-nel\",\"max_age\":604800,\"endpoints\":[{\"url\":\"https://a.nel.cloudflare.com/report/v4?s=PUCbk0h9AOERr%2B2xR0N6bm%2B24Zq%2Bh4GDVp04aSm%2F33FsEEiwXM3IwzWLa0GPuvKTDnHpGcvTxVgnSs9MZ19r8qpspUnjByBGJQ%3D%3D\"}]}",
          "server": "cloudflare",
          "speculation-rules": "\"/cdn-cgi/speculation\"",
          "vary": "RSC, Next-Router-State-Tree, Next-Router-Prefetch, Next-Url, Accept-Encoding",
          "x-nextjs-cache": "HIT",
          "x-powered-by": "Next.js"
        },
        "http_version": "HTTP/1.1",
        "redirect_chain": [],
        "start_url": "https://weyhro.hk",
        "status": 200
      },
      "lastscrape": "2026-03-20 19:02:48.670312",
      "slug": "https://weyhro.hk",
      "title": "Weyhro",
      "type": "DLS",
      "updated": "2026-03-20 19:02:48.670312"
    }
  ],
  "meta": null,
  "name": "weyhro",
  "parser": true,
  "profile": [],
  "tools": [],
  "ttps": [],
  "url": "https://www.ransomware.live/group/weyhro"
}